pyGallica/LICENSE
pyGallica/README.md
pyGallica/__init__.py
pyGallica/cli.py
pyGallica/client.py
pyGallica/exceptions.py
pyGallica/models.py
pyGallica/parser.py
pyGallica/record.py
pyGallica/search.py
pygallica-0.1.0.dist-info/METADATA
pygallica-0.1.0.dist-info/WHEEL
pygallica-0.1.0.dist-info/licenses/LICENSE
pygallica-0.1.0.dist-info/RECORD
