Metadata-Version: 2.4
Name: pyGallica
Version: 0.1.0
Summary: Lightweight Python wrapper for Gallica (BnF) SRU & IIIF.
Project-URL: Homepage, https://github.com/your-username/pyGallica
Project-URL: Issues, https://github.com/your-username/pyGallica/issues
Author-email: Your Name <you@example.com>
License: MIT
License-File: LICENSE
Requires-Python: >=3.10
Requires-Dist: httpx<1.0,>=0.27
Provides-Extra: pandas
Requires-Dist: pandas>=2.0; extra == 'pandas'
